labrepo_test/__init__.py
labrepo_test/labrepo_test.py
labrepo_test/SubPackage1/MyClass1.py
labrepo_test/SubPackage1/__init__.py
labrepo_test/SubPackage2/MyClass2.py
labrepo_test/SubPackage2/MyClass3.py
labrepo_test/SubPackage2/__init__.py
tests/__init__.py
tests/test_labrepo_test.py
labrepo_test-0.3.0.dist-info/AUTHORS.rst
labrepo_test-0.3.0.dist-info/LICENSE
labrepo_test-0.3.0.dist-info/METADATA
labrepo_test-0.3.0.dist-info/WHEEL
labrepo_test-0.3.0.dist-info/top_level.txt
labrepo_test-0.3.0.dist-info/RECORD
