Metadata-Version: 2.1
Name: labrepo-test
Version: 0.3.0
Summary: Testing Travis CI + codecov + automatic deployment
Home-page: https://github.com/vigji/labrepo_test
Author: Luigi Petrucco
Author-email: luigi.petrucco@gmail.com
License: GNU General Public License v3
Keywords: labrepo_test
Platform: UNKNOWN
Classifier: Development Status :: 2 - Pre-Alpha
Classifier: Intended Audience :: Developers
Classifier: License :: OSI Approved :: GNU General Public License v3 (GPLv3)
Classifier: Natural Language :: English
Classifier: Programming Language :: Python :: 3
Classifier: Programming Language :: Python :: 3.6
Classifier: Programming Language :: Python :: 3.7
Classifier: Programming Language :: Python :: 3.8
Requires-Python: >=3.6
